psc/lib/EOmodule.py
psc/lib/MCin2DPS_EPA.py
psc/lib/MCin2DPS_nEPA.py
psc/lib/MCinNDPS_EPA.py
psc/lib/__init__.py
psc/lib/createfolder.py
psc/lib/g_space.py
psc/lib/getscatteringfactor.py
psc/lib/x2Dlinearization.py
psc/lib/x2Dpolygon.py
psc/lib/x2Drepetition.py
psc/lib/x2Dwritesolution.py
psc/lib/x3Dchecklinearization.py
psc/lib/x3Dintersection.py
psc/lib/x3DlinearizationEPA.py
psc/lib/x3DlinearizationnEPA.py
psc/lib/x3Dreadwrite.py
psc/lib/x3Drepetition.py
psc/lib/xlinearizationtools.py
psc/test/test1.py
psc/tools/__init__.py
psc/tools/analyzehklfile.py
psc/tools/clusteringsolution.py
psc/tools/experimentalstructureNDPS.py
psc/tools/functionsforMC.py
psc/tools/plot3DMCresults.py
psc/tools/plottime.py
psc/tools/x2Dplot.py
psc/tools/x3Dplot.py
psc/tools/xplottime.py
pypsc-0.2.1.dist-info/LICENSE
pypsc-0.2.1.dist-info/METADATA
pypsc-0.2.1.dist-info/WHEEL
pypsc-0.2.1.dist-info/top_level.txt
pypsc-0.2.1.dist-info/RECORD
