Metadata-Version: 2.1
Name: pypsc
Version: 0.2.1
Summary: Predict crystal structures from available hkl information
Author: Melanie Netwich, Matthias Zschornak
Author-email: Muthu Vallinayagam <muthu.vallinayagam@htw-dresden.de>
Maintainer-email: Muthu Vallinayagam <muthu.vallin@gmail.com>
License: MIT License
Project-URL: Documentation, https://github.com/mvnayagam/pypsc.git
Project-URL: Repository, https://github.com/mvnayagam/pypsc.git
Project-URL: Issues, https://github.com/mvnayagam/pypsc/issues
Keywords: x-ray,miller index,python,structure prediction,inequalities,polytope,parameter space,one-dimensionally projected structures
Requires-Python: >=3.10
License-File: LICENSE
Requires-Dist: numpy>=1.24.0
Requires-Dist: h5py>=3.11.0
Requires-Dist: cvxopt>=1.3.2
Requires-Dist: polytope>=0.2.5
Requires-Dist: scipy>=1.14.1
Requires-Dist: shapely>=2.0.6
Requires-Dist: matplotlib>=3.9.0
Requires-Dist: pandas>=2.0.0
Requires-Dist: intvalpy>=1.6.0
